{
  "_format": "hh-sol-cache-2",
  "files": {
    "C:\\Users\\Abhishek Jha\\Desktop\\assignment\\contracts\\Operations.sol": {
      "lastModificationDate": 1681208699820,
      "contentHash": "1fffb7ac4d01174360e2476af2c47d1e",
      "sourceName": "contracts/Operations.sol",
      "solcConfig": {
        "version": "0.8.1",
        "settings": {
          "optimizer": {
            "enabled": false,
            "runs": 200
          },
          "outputSelection": {
            "*": {
              "*": [
                "abi",
                "evm.bytecode",
                "evm.deployedBytecode",
                "evm.methodIdentifiers",
                "metadata"
              ],
              "": [
                "ast"
              ]
            }
          }
        }
      },
      "imports": [],
      "versionPragmas": [
        "^0.8.0"
      ],
      "artifacts": [
        "Operations"
      ]
    }
  }
}
